nbdump/__init__.py
nbdump/cli.py
nbdump/core.py
nbdump-0.0.3.dist-info/LICENSE
nbdump-0.0.3.dist-info/METADATA
nbdump-0.0.3.dist-info/WHEEL
nbdump-0.0.3.dist-info/entry_points.txt
nbdump-0.0.3.dist-info/top_level.txt
nbdump-0.0.3.dist-info/RECORD
