Metadata-Version: 2.1
Name: nbdump
Version: 0.0.3
Summary: Dump files to Jupyter notebook.
Author-email: Evan Arlian <evanarlian2000@gmail.com>
License: MIT License
Project-URL: Homepage, https://github.com/evanarlian/nbdump
Keywords: jupyter,notebook,kaggle
Classifier: Programming Language :: Python :: 3
Classifier: License :: OSI Approved :: MIT License
Classifier: Operating System :: OS Independent
Requires-Python: >=3.9
License-File: LICENSE
Requires-Dist: nbformat
